pd_tlidemo/__init__.py
pd_tlidemo/tliDemo.py
pd_tlidemo-0.6.dist-info/DESCRIPTION.rst
pd_tlidemo-0.6.dist-info/METADATA
pd_tlidemo-0.6.dist-info/RECORD
pd_tlidemo-0.6.dist-info/WHEEL
pd_tlidemo-0.6.dist-info/metadata.json
pd_tlidemo-0.6.dist-info/top_level.txt
