Metadata-Version: 2.0
Name: pd-tlidemo
Version: 0.6
Summary: Thought Leader Identification Analysis
Home-page: https://bi4c-11663-mastermanager.bi.services.bluemix.net:7052/webapps/webapp/gen-tli
Author: IBM Stampede
Author-email: smazumder@us.ibm.com
License: Apache 2.0
Platform: UNKNOWN
Requires-Dist: pixiedust
